datas/__init__.py
datas/datas.py
datas-0.2.8.data/scripts/init
datas-0.2.8.dist-info/LICENSE
datas-0.2.8.dist-info/METADATA
datas-0.2.8.dist-info/WHEEL
datas-0.2.8.dist-info/top_level.txt
datas-0.2.8.dist-info/RECORD
